<?xml version="1.0" encoding="utf-8"?>
<data-map xmlns="http://cayenne.apache.org/schema/11/modelMap"
	 xmlns:xsi="http://www.w3.org/2001/XMLSchema-instance"
	 xsi:schemaLocation="http://cayenne.apache.org/schema/11/modelMap https://cayenne.apache.org/schema/11/modelMap.xsd"
	 project-version="11">
	<property name="defaultPackage" value="cayng.data"/>
	<db-entity name="person">
		<db-attribute name="id" type="INTEGER" isPrimaryKey="true" isGenerated="true" isMandatory="true"/>
		<db-attribute name="name" type="VARCHAR" length="50"/>
	</db-entity>
	<obj-entity name="Person" className="cayng.data.Person" dbEntityName="person">
		<obj-attribute name="nom" type="java.lang.String" db-attribute-path="name"/>
	</obj-entity>
	<cgen xmlns="http://cayenne.apache.org/schema/11/cgen">
		<name>Default</name>
		<destDir>../../java</destDir>
		<mode>entity</mode>
		<template>templates/v4_1/subclass.vm</template>
		<superTemplate>templates/v4_1/superclass.vm</superTemplate>
		<embeddableTemplate>templates/v4_1/embeddable-subclass.vm</embeddableTemplate>
		<embeddableSuperTemplate>templates/v4_1/embeddable-superclass.vm</embeddableSuperTemplate>
		<dataMapTemplate>templates/v4_1/datamap-subclass.vm</dataMapTemplate>
		<dataMapSuperTemplate>templates/v4_1/datamap-superclass.vm</dataMapSuperTemplate>
		<outputPattern>*.java</outputPattern>
		<makePairs>true</makePairs>
		<usePkgPath>true</usePkgPath>
		<overwrite>false</overwrite>
		<createPropertyNames>false</createPropertyNames>
		<createPKProperties>true</createPKProperties>
	</cgen>
</data-map>
